{"page":0,"pageSize":36,"list":[{"title":"机车骑士","id":18284,"date":"2019/7/16 07:00:00","imageFilename":"50ea6be6f5a2c9c69878fb27fe1cba0e.jpeg","bigImageFilename":"25274df07b01f2e4b0f272d7094fbd4f.jpeg","tags":["好身材","害羞","欧美","游客投稿","美","美腿"],"width":1080,"height":864},{"title":"不好意思了","id":9536,"date":"2017/5/12 21:32:00","imageFilename":"bc1944f187c84fc2a9552dd4dbd0eaca.jpeg","bigImageFilename":"5c33ce9a8e20c35ef4c64ff025ac3a37.jpeg","tags":["害羞"],"width":500,"height":666},{"title":"别害羞","id":4349,"date":"2016/1/21 23:21:00","imageFilename":"3a3b49c4d62fb7a6e138750d332f97d3.jpeg","bigImageFilename":"1d2cab15136329d166e320d50b1abc48.jpeg","tags":["害羞","风景"],"width":600,"height":800},{"title":"小蛮腰","id":3329,"date":"2015/6/18 08:25:00","imageFilename":"2755ca95ac7f34276a9cfb57300c1978.jpeg","bigImageFilename":"1a93abb38c528c3168698fa7c98a083b.jpeg","tags":["好身材","害羞"],"width":640,"height":640},{"title":"我喜欢牛仔裤","id":2372,"date":"2015/11/24 21:23:00","imageFilename":"218d17a77cd6afb5a3da9f222a70008b.jpeg","bigImageFilename":"c60ab922cc1f2fcbb9e0a01e04fdfcb6.jpeg","tags":["害羞"],"width":383,"height":835},{"title":"第一次下厨","id":1524,"date":"2015/10/18 19:20:00","imageFilename":"47cce8b56d083d2da754fd8490d3b303.jpeg","bigImageFilename":"7f429d719d625845f1035d91aa6a418e.jpeg","tags":["好身材","害羞","贵在真实"],"width":500,"height":621},{"title":"害羞了。。。","id":33,"date":"2014/7/23 14:14:00","imageFilename":"1b8baddf08311f7e8da97b7401495417.jpeg","bigImageFilename":"3a8ce4e20f6060b129b04ee4a0dec413.jpeg","tags":["害羞"],"width":151,"height":244}],"updateTime":"2024/7/13 04:30:31","allTags":["美腿","贵在真实","在路上","好身材","大","美","游客投稿","风景","趣图","欧美","害羞"],"total":7,"totalPage":1}